strcond/__init__.py
strcond/test.py
strcond-0.1.0.dist-info/METADATA
strcond-0.1.0.dist-info/WHEEL
strcond-0.1.0.dist-info/top_level.txt
strcond-0.1.0.dist-info/RECORD
