Metadata-Version: 2.1
Name: strcond
Version: 0.1.0
Summary: A tool to determine whether a given string (such as HTML) meets the conditions of a query that combines 'and' and 'or' conditions.
Home-page: https://github.co.jp/
Author: bib_inf
Author-email: contact.bibinf@gmail.com
License: CC0 v1.0
Classifier: Programming Language :: Python :: 3
Classifier: License :: CC0 1.0 Universal (CC0 1.0) Public Domain Dedication
Requires-Dist: ezpip
Requires-Dist: sout (>=1.2.1)
Requires-Dist: relpath
